certbot_dns_kas/__init__.py
certbot_dns_kas/_internal/__init__.py
certbot_dns_kas/_internal/dns_kas.py
certbot_dns_kas-0.1.2.dist-info/licenses/LICENSE
tests/__init__.py
tests/test_dns_kas.py
certbot_dns_kas-0.1.2.dist-info/METADATA
certbot_dns_kas-0.1.2.dist-info/WHEEL
certbot_dns_kas-0.1.2.dist-info/entry_points.txt
certbot_dns_kas-0.1.2.dist-info/top_level.txt
certbot_dns_kas-0.1.2.dist-info/RECORD
